bidir_shift_reg.v
module bidir_shift_reg #(parameter MSB=8) (
  input d,
  input clk,
  input en,
  input dir,
  input circular,
  input rstn,
  output reg [MSB-1:0] out
);
always @(posedge clk) begin
  if (!rstn)
    out <= 0;
  else begin
    if (en) begin
      if (circular) begin
        if (dir)
          out <= {out[0], out[MSB-1:1]};
        else
          out <= {out[MSB-2:0], out[MSB-1]};
      end 
      else begin
        if (dir)
          out <= {out[MSB-2:0], d};
        else
          out <= {d, out[MSB-1:1]};
      end
    end 
    else
      out <= out;
  end
end
endmodule

shift_reg_tb.v
module shift_reg_tb;
   parameter MSB = 8;        // [Optional] Declare a parameter to represent number of bits in shift register  
  reg d, clk, en, dir, circular, rstn;
  wire [MSB-1:0] out;
  
  // Instantiate the shift_reg module
  bidir_shift_reg #(MSB) dut (
    .d(d),
    .clk(clk),
    .en(en),
    .dir(dir),
    .circular(circular),
    .rstn(rstn),
    .out(out)
  );
  initial begin
      $dumpfile("shift_tb_sr.vcd");
        $dumpvars(0, shift_reg_tb);
   end

  // Clock generator
  always begin
    clk = 0;
    #5;
    clk = 1;
    #5;
  end
  
  // Initialize inputs
  initial begin
    d = 0;
    en = 0;
    dir = 0;
    circular = 0;
    rstn = 0;
    
    // Apply reset
    rstn = 0;
    #10;
    rstn = 1;
    
    // Test case 1: Bidirectional shift to the left
    #10;
    en = 1;
    dir = 0;
    d = 1;
    #10;
    d = 0;
    #10;
    
    // Test case 2: Bidirectional shift to the right
    dir = 1;
    d = 1;
    #10;
    d = 0;
    #10;
    
    // Test case 3: Circular shift to the left
    circular = 1;
    dir = 0;
    d = 1;
    #10;
    d = 0;
    #10;
    
    // Test case 4: Circular shift to the right
    dir = 1;
    d = 1;
    #10;
    d = 0;
    #10;
    
    // End simulation
    $finish;
    

  end
  always @(posedge clk) begin
        // display the value of the shift register, out, circular, dir
        $display("out = %b, circular = %b, dir = %b", out, circular, dir);
  end
  
endmodule

shift_tb_sr.vcd
$date
	Fri May 12 00:11:45 2023
$end
$version
	Icarus Verilog
$end
$timescale
	1s
$end
$scope module shift_reg_tb $end
$var wire 8 ! out [7:0] $end
$var parameter 32 " MSB $end
$var reg 1 # circular $end
$var reg 1 $ clk $end
$var reg 1 % d $end
$var reg 1 & dir $end
$var reg 1 ' en $end
$var reg 1 ( rstn $end
$scope module dut $end
$var wire 1 # circular $end
$var wire 1 $ clk $end
$var wire 1 % d $end
$var wire 1 & dir $end
$var wire 1 ' en $end
$var wire 1 ( rstn $end
$var parameter 32 ) MSB $end
$var reg 8 * out [7:0] $end
$upscope $end
$upscope $end
$enddefinitions $end
$comment Show the parameter values. $end
$dumpall
b1000 )
b1000 "
$end
#0
$dumpvars
bx *
0(
0'
0&
0%
0$
0#
bx !
$end
#5
b0 !
b0 *
1$
#10
0$
1(
#15
1$
#20
0$
1%
1'
#25
b10000000 !
b10000000 *
1$
#30
0$
0%
#35
b1000000 !
b1000000 *
1$
#40
0$
1%
1&
#45
b10000001 !
b10000001 *
1$
#50
0$
0%
#55
b10 !
b10 *
1$
#60
0$
1%
0&
1#
#65
b100 !
b100 *
1$
#70
0$
0%
#75
b1000 !
b1000 *
1$
#80
0$
1%
1&
#85
b100 !
b100 *
1$
#90
0$
0%
#95
b10 !
b10 *
1$
